confinety/__init__.py
confinety/configurations.py
confinety/parameters.py
confinety/sections.py
confinety-0.0.1.dist-info/licenses/LICENSE
confinety-0.0.1.dist-info/METADATA
confinety-0.0.1.dist-info/WHEEL
confinety-0.0.1.dist-info/top_level.txt
confinety-0.0.1.dist-info/RECORD
