Metadata-Version: 2.4
Name: confinety
Version: 0.0.1
Summary: Package for automation the process of creating INI configuration files.
Author-email: Barak Goldberg <goldberg.b@gmail.com>
License-Expression: MIT
Project-URL: Homepage, https://github.com/goldbergb/confinety
Project-URL: Issues, https://github.com/goldbergb/confinety/issues
Classifier: Programming Language :: Python :: 3
Classifier: Operating System :: OS Independent
Requires-Python: >=3.8
License-File: LICENSE
Requires-Dist: python-dateutil==2.9.0.post0
Requires-Dist: pytz==2025.2
Requires-Dist: six==1.17.0
Requires-Dist: tzdata==2025.2
Dynamic: license-file
